junkpurge/__init__.py
junkpurge-0.1.0.dist-info/METADATA
junkpurge-0.1.0.dist-info/WHEEL
junkpurge-0.1.0.dist-info/entry_points.txt
junkpurge-0.1.0.dist-info/top_level.txt
junkpurge-0.1.0.dist-info/RECORD
