Metadata-Version: 2.1
Name: junkpurge
Version: 0.1.0
Summary: A tool to clean up build directories in various programming languages.
Home-page: https://github.com/saurabhchalke/JunkPurge
Author: Saurabh Chalke
Author-email: saurabh.chalke@example.com
Classifier: Programming Language :: Python :: 3
Classifier: License :: OSI Approved :: MIT License
Classifier: Operating System :: OS Independent
Requires-Python: >=3.6
